lib_dzne_tsv/__init__.py
lib_dzne_tsv-0.2.3.dist-info/LICENSE.txt
lib_dzne_tsv-0.2.3.dist-info/METADATA
lib_dzne_tsv-0.2.3.dist-info/WHEEL
lib_dzne_tsv-0.2.3.dist-info/top_level.txt
lib_dzne_tsv-0.2.3.dist-info/RECORD
