Metadata-Version: 2.1
Name: lib-dzne-tsv
Version: 0.2.3
Summary: Libary for handling tsv-data.
Author-email: Johannes Programming <johannes-programming@posteo.org>
License: The MIT License (MIT)
Project-URL: Download, https://pypi.org/project/lib-dzne-tsv/#files
Project-URL: Source, https://github.com/johannes-programming/lib_dzne_tsv
Classifier: License :: OSI Approved :: MIT License
Classifier: Programming Language :: Python
Classifier: Programming Language :: Python :: 3
Requires-Python: >=3.11
License-File: LICENSE.txt
Requires-Dist: pandas >=1.4.2
Requires-Dist: lib-dzne-filedata >=0.4.0
Requires-Dist: simple-tsv >=1.0.0
